pipes/__init__.py
pipes_compat-1.1.0.dist-info/METADATA
pipes_compat-1.1.0.dist-info/WHEEL
pipes_compat-1.1.0.dist-info/licenses/LICENSE
pipes_compat-1.1.0.dist-info/RECORD
