Metadata-Version: 2.4
Name: pipes-compat
Version: 1.1.0
Summary: Compatibility shim for Python's removed pipes module (Python 3.13+)
Project-URL: Homepage, https://github.com/Grochocinski/pipes-compat
Project-URL: Repository, https://github.com/Grochocinski/pipes-compat
Project-URL: Issues, https://github.com/Grochocinski/pipes-compat/issues
Project-URL: PyPI, https://pypi.org/project/pipes-compat/
Author-email: William Grochocinski <williamgrochocinski@gmail.com>
License: Apache-2.0
License-File: LICENSE
Classifier: Development Status :: 4 - Beta
Classifier: Intended Audience :: Developers
Classifier: License :: OSI Approved :: Apache Software License
Classifier: Programming Language :: Python :: 3
Classifier: Programming Language :: Python :: 3.13
Classifier: Programming Language :: Python :: 3.14
Classifier: Topic :: Software Development :: Libraries :: Python Modules
Classifier: Topic :: System :: Systems Administration
Requires-Python: >=3.13
